artifex/__init__.py
artifex/__version__.py
artifex/config.py
artifex/py.typed
artifex/utils.py
artifex/core/__init__.py
artifex/core/_hf_patches.py
artifex/core/exceptions.py
artifex/core/log_shipper.py
artifex/core/models.py
artifex/core/decorators/__init__.py
artifex/core/decorators/auto_validation.py
artifex/core/decorators/logging.py
artifex/models/__init__.py
artifex/models/base_model.py
artifex/models/classification/__init__.py
artifex/models/classification/classification_model.py
artifex/models/classification/binary_classification/__init__.py
artifex/models/classification/binary_classification/guardrail/__init__.py
artifex/models/classification/binary_classification/spam_detection/__init__.py
artifex/models/classification/multi_class_classification/__init__.py
artifex/models/classification/multi_class_classification/emotion_detection/__init__.py
artifex/models/classification/multi_class_classification/intent_classifier/__init__.py
artifex/models/classification/multi_class_classification/sentiment_analysis/__init__.py
artifex/models/classification/multi_class_classification/topic_classification/__init__.py
artifex/models/named_entity_recognition/__init__.py
artifex/models/named_entity_recognition/named_entity_recognition.py
artifex/models/named_entity_recognition/text_anonymization/__init__.py
artifex/models/reranker/__init__.py
artifex/models/reranker/reranker.py
artifex-0.6.0.dist-info/licenses/LICENSE
assets/hero.png
assets/platform-inference-logs.png
assets/platform-warnings.png
tests/__init__.py
tests/conftest.py
tests/integration/__init__.py
tests/integration/emotion_detection/test_ed__call__intgr.py
tests/integration/emotion_detection/test_ed_train_intgr.py
tests/integration/guardrail/test_gr__call__intgr.py
tests/integration/guardrail/test_gr_train_intgr.py
tests/integration/intent_classifier/test_ic__call__intgr.py
tests/integration/intent_classifier/test_ic_train_intgr.py
tests/integration/named_entity_recognition/test_ner__call__intgr.py
artifex-0.6.0.dist-info/METADATA
artifex-0.6.0.dist-info/WHEEL
artifex-0.6.0.dist-info/top_level.txt
artifex-0.6.0.dist-info/RECORD
