Metadata-Version: 2.4
Name: artifex
Version: 0.6.0
Summary: Create your private AI model with no training data or GPUs 🤖🚀.
Author-email: Riccardo Lucato <riccardo@tanaos.com>
License: MIT
Project-URL: homepage, https://github.com/tanaos/artifex
Classifier: Development Status :: 3 - Alpha
Classifier: Intended Audience :: Developers
Classifier: License :: OSI Approved :: MIT License
Classifier: Programming Language :: Python :: 3.10
Classifier: Topic :: Software Development :: Libraries :: Python Modules
Classifier: Operating System :: OS Independent
Requires-Python: >=3.10
License-File: LICENSE
Requires-Dist: aiohttp>=3.13.3
Requires-Dist: datasets>=3.6.0
Requires-Dist: filelock>=3.20.3
Requires-Dist: jupyterlab>=4.4.8
Requires-Dist: protobuf>=6.33.2
Requires-Dist: rich>=14.1.0
Requires-Dist: sentencepiece>=0.2.1
Requires-Dist: synthex>=0.4.2
Requires-Dist: tiktoken>=0.12.0
Requires-Dist: torch>=2.8.0
Requires-Dist: transformers[torch]>=4.53.1
Requires-Dist: tzlocal>=5.3.1
Requires-Dist: urllib3>=2.6.3
Dynamic: license-file
